{"id": "os.path", "path": "C:\\ProgramData\\Anaconda3\\Lib\\mypy\\typeshed\\stdlib\\3\\os\\path.pyi", "mtime": 1522534016, "size": 3628, "hash": "5bcfba236688f555c29c7ee5a234e7eb", "data_mtime": 1524602909, "dependencies": ["sys", "typing", "builtins"], "suppressed": [], "child_modules": [], "options": {"warn_unused_ignores": false, "ignore_errors": false, "disallow_untyped_decorators": false, "ignore_missing_imports": true, "show_none_errors": true, "disallow_untyped_calls": false, "no_implicit_optional": false, "platform": "win32", "quick_and_dirty": false, "disallow_untyped_defs": false, "disallow_any_expr": false, "strict_boolean": false, "follow_imports": "silent", "disallow_any_explicit": false, "disallow_any_generics": false, "disallow_subclassing_any": false, "disallow_any_unimported": false, "strict_optional_whitelist": null, "warn_return_any": false, "disallow_any_decorated": false, "cache_fine_grained": false, "strict_optional": false, "check_untyped_defs": false, "warn_no_return": true}, "dep_prios": [10, 5, 5], "dep_lines": [6, 7, 15], "interface_hash": "b09ce9735c7fa7b88c02ee1c23ccc107", "version_id": "0.580", "ignore_all": false}
